[
  {
    "access": "1",
    "id": "0000000023",
    "name": "Юлия",
    "hash": 922910611384182817
  },
  {
    "access": "2",
    "id": "0000000056",
    "name": "Никита",
    "hash": 6096180312941131800
  },
  {
    "access": "3",
    "id": "0000000024",
    "name": "Полина",
    "hash": 2849344053005781643
  },
  {
    "access": "3",
    "id": "0000000057",
    "name": "Виктория",
    "hash": -3880221716735003549
  },
  {
    "access": "4",
    "id": "0000000096",
    "name": "Ирина",
    "hash": -8118064881735605494
  },
  {
    "access": "5",
    "id": "0000000123",
    "name": "Андрей",
    "hash": -4166265234480232341
  },
  {
    "access": "6",
    "id": "0000000012",
    "name": "Игорь",
    "hash": 7311791911831199689
  },
  {
    "access": "7",
    "id": "0000000013",
    "name": "Игнат",
    "hash": 1918013083195247267
  },
  {
    "access": "7",
    "id": "0000000017",
    "name": "Тимур",
    "hash": 3706162965631382441
  }
]